README.md
setup.py
calculate_retention/__init__.py
calculate_retention/calculate_retention.py
calculate_retention.egg-info/PKG-INFO
calculate_retention.egg-info/SOURCES.txt
calculate_retention.egg-info/dependency_links.txt
calculate_retention.egg-info/not-zip-safe
calculate_retention.egg-info/requires.txt
calculate_retention.egg-info/top_level.txt